Workbook
Name AC: #REF!
Name AC: #REF!
Name ACC: #REF!
Name ACC: #REF!
Name actividades_tarifas: '[1]Actividades '!$B$12:$J$40
Name AD: #REF!
Name AD: #REF!
Name Año_1: #REF!
Name Año_1: #REF!
Name Año_2: #REF!
Name Año_2: #REF!
Name AOP: #REF!
Name ARL: [2]Tablas!$A$12:$B$17
Name ARL: [3]Tablas!$A$12:$B$17
Name AS: #REF!
Name AS: #REF!
Name BE: #REF!
Name BE: #REF!
Name Bimestralmente: #REF!
Name Bimestralmente: #REF!
Name BP_APERTURA: #REF!
Name BP_Diciembre_Año_2: #REF!
Name BP_Enero_Año_1: #REF!
Name CIR: #REF!
Name Codigo_Ctro_Costos_Grupo: #REF!
Name Codigo_CtroCostos: #REF!
Name Codigo1: [4]Año_1!$A$1:$A$65536
Name Codigos_PUC: #REF!
Name Codigos_PUC: #REF!
Name CR: #REF!
Name CR: #REF!
Name Cuatrimestralmente: #REF!
Name Cuatrimestralmente: #REF!
Name CV: #REF!
Name DC: #REF!
Name DII: [5]Normativa!$E$46:$F$55
Name DIP: [5]Normativa!$M$20:$N$29
Name ECP: #REF!
Name ECP: #REF!
Name ECPC: #REF!
Name ECPC: #REF!
Name EFE: #REF!
Name EFE: #REF!
Name EGC: [5]Normativa!$N$162:$O$171
Name ENGC: [5]Normativa!$J$162:$K$261
Name ERC: #REF!
Name ERC: #REF!
Name ETC: #REF!
Name ETC: #REF!
Name EYE: #REF!
Name EYE: #REF!
Name GCI: [5]Normativa!$E$33:$F$42
Name GCII: [5]Normativa!$I$33:$J$42
Name GCIII: [5]Normativa!$M$33:$N$42
Name GIMP: #REF!
Name GIMP: #REF!
Name GMF: [5]Normativa!$J$59:$M$110
Name GTOS: #REF!
Name GTOS: #REF!
Name HTEFE: #REF!

Sheet Copyright
C15: https://actualicese.com/formato-de-flujo-de-caja-real-y-presupuestado/

Sheet Empieza aquí

Sheet Introducción
B2: Formato de flujo de caja real y presupuestado
B4: (Fecha de actualización: agosto 29 de 2024)
B6: Te presentamos un modelo de flujo de caja real y presupuestado de los cobros y pagos mensuales que realiza una entidad. Te permitirá hacer seguimiento al disponible de una empresa y visualizar a través de alertas y gráficos la variación real vs. lo presupuestado.
B8: Contenido
B10: - Línea con el saldo inicial del disponible real y presupuestado al inicio del mes.
B11: - Entradas reales y presupuestadas en el mes.
B12: - Valor disponible real y presupuestado en el mes (saldo inicial más las entradas).
B13: - Salidas reales y presupuestadas en el mes.
B14: - Sobrante o faltante real y presupuestado del mes (entradas menos salidas).
B15: - Valor disponible real y presupuestado al final del período (saldo inicial más el sobrante o faltante).
B16: - Alertas de las variaciones de los saldos reales vs. los presupuestados.
B17: - Gráfico resumen con el disponible al final de cada período.
... B39: Esta plantilla en Excel permite el control mensual de los consumos y pagos de servicios públicos, ajustándose a las necesidades de cada empresa. Podrás medir el gasto de servicios públicos mes a mes; además, automáticamente se generará una gráfica comparativa que te permitirá monitorear las desviaciones.

Sheet Flujo de caja
B5: Formato de flujo de caja real y presupuestado
B7: =+Introducción!$B$4 -> (Fecha de actualización: agosto 29 de 2024)
B9: Flujo de caja | C9: AÑO
C10: Enero | F10: Febrero | I10: Marzo | L10: Abril | O10: Mayo | R10: Junio | U10: Julio | X10: Agosto | AA10: Septiembre | AD10: Octubre | AG10: Noviembre | AJ10: Diciembre
C11: Ppto | D11: Real | E11: Var % | F11: Ppto | G11: Real | H11: Var % | I11: Ppto | J11: Real | K11: Var % | L11: Ppto | M11: Real | N11: Var % | O11: Ppto | P11: Real | Q11: Var % | R11: Ppto | S11: Real | T11: Var % | U11: Ppto | V11: Real | W11: Var % | X11: Ppto | Y11: Real | Z11: Var % | AA11: Ppto | AB11: Real | AC11: Var % | AD11: Ppto | AE11: Real | AF11: Var % | AG11: Ppto | AH11: Real | AI11: Var % | AJ11: Ppto | AK11: Real | AL11: Var %
B12: Saldo inicial (cifras expresadas en pesos colombianos) | C12: 111000000 | D12: 112333000 | E12: =IFERROR(D12/C12-1,"") -> 0.012009009 | F12: =C57 -> 131500000 | G12: =D57 -> 125221000 | H12: =IFERROR(G12/F12-1,"") -> -0.047749049 | I12: =F57 -> 179500000 | J12: =G57 -> 157253000 | K12: =IFERROR(J12/I12-1,"") -> -0.12393872 | L12: =I57 -> 185500000 | M12: =J57 -> 165284000 | N12: =IFERROR(M12/L12-1,"") -> -0.10898113 | O12: =L57 -> 219500000 | P12: =M57 -> 198487000 | Q12: =IFERROR(P12/O12-1,"") -> -0.095731207 | R12: =O57 -> 226500000 | S12: =P57 -> 209523000 | T12: =IFERROR(S12/R12-1,"") -> -0.074953642 | U12: =R57 -> 262500000 | V12: =S57 -> 247408000 | W12: =IFERROR(V12/U12-1,"") -> -0.057493333 | X12: =U57 -> 294500000 | Y12: =V57 -> 256905000 | Z12: =IFERROR(Y12/X12-1,"") -> -0.12765705 | AA12: =X57 -> 332500000 | AB12: =Y57 -> 289788950 | AC12: =IFERROR(AB12/AA12-1,"") -> -0.12845429 | AD12: =AA57 -> 366500000 | AE12: =AB57 -> 324918850 | AF12: =IFERROR(AE12/AD12-1,"") -> -0.11345471 | AG12: =AD57 -> 417500000 | AH12: =AE57 -> 363717460 | AI12: =IFERROR(AH12/AG12-1,"") -> -0.12882046 | AJ12: =AG57 -> 466500000 | AK12: =AH57 -> 416333510 | AL12: =IFERROR(AK12/AJ12-1,"") -> -0.10753803
B14: Entradas
B15: Ventas | C15: 80000000 | D15: 75789000 | E15: =IFERROR(D15/C15-1,"") -> -0.0526375 | F15: 80000000 | G15: 80010000 | H15: =IFERROR(G15/F15-1,"") -> 0.000125 | I15: 80000000 | J15: 81190000 | K15: =IFERROR(J15/I15-1,"") -> 0.014875 | L15: 90000000 | M15: 90000000 | N15: =IFERROR(M15/L15-1,"") -> 0 | O15: 90000000 | P15: 86120000 | Q15: =IFERROR(P15/O15-1,"") -> -0.043111111 | R15: 90000000 | S15: 89563000 | T15: =IFERROR(S15/R15-1,"") -> -0.0048555556 | U15: 100000000 | V15: 88000000 | W15: =IFERROR(V15/U15-1,"") -> -0.12 | X15: 100000000 | Y15: 95111000 | Z15: =IFERROR(Y15/X15-1,"") -> -0.04889 | AA15: 100000000 | AB15: 99026000 | AC15: =IFERROR(AB15/AA15-1,"") -> -0.00974 | AD15: 120000000 | AE15: 102102000 | AF15: =IFERROR(AE15/AD15-1,"") -> -0.14915 | AG15: 120000000 | AH15: 108005000 | AI15: =IFERROR(AH15/AG15-1,"") -> -0.099958333 | AJ15: 120000000 | AK15: 125459000 | AL15: =IFERROR(AK15/AJ15-1,"") -> 0.045491667
B16: Recaudo de cartera | C16: 25000000 | D16: 22900000 | E16: =IFERROR(D16/C16-1,"") -> -0.084 | F16: 25000000 | G16: 15240000 | H16: =IFERROR(G16/F16-1,"") -> -0.3904 | I16: 25000000 | J16: 26350000 | K16: =IFERROR(J16/I16-1,"") -> 0.054 | L16: 28000000 | M16: 25000000 | N16: =IFERROR(M16/L16-1,"") -> -0.10714286 | O16: 28000000 | P16: 20000000 | Q16: =IFERROR(P16/O16-1,"") -> -0.28571429 | R16: 28000000 | S16: 27350000 | T16: =IFERROR(S16/R16-1,"") -> -0.023214286 | U16: 30000000 | V16: 20000000 | W16: =IFERROR(V16/U16-1,"") -> -0.33333333 | X16: 30000000 | Y16: 29645000 | Z16: =IFERROR(Y16/X16-1,"") -> -0.011833333 | AA16: 30000000 | AB16: 28888000 | AC16: =IFERROR(AB16/AA16-1,"") -> -0.037066667 | AD16: 33000000 | AE16: 31697000 | AF16: =IFERROR(AE16/AD16-1,"") -> -0.039484848 | AG16: 33000000 | AH16: 39500000 | AI16: =IFERROR(AH16/AG16-1,"") -> 0.1969697 | AJ16: 33000000 | AK16: 32900000 | AL16: =IFERROR(AK16/AJ16-1,"") -> -0.003030303
B17: Préstamos bancarios solicitados | C17: 0 | D17: 0 | E17: =IFERROR(D17/C17-1,"") | F17: 0 | G17: 0 | H17: =IFERROR(G17/F17-1,"") | I17: 0 | J17: 0 | K17: =IFERROR(J17/I17-1,"") | L17: 0 | M17: 0 | N17: =IFERROR(M17/L17-1,"") | O17: 0 | P17: 0 | Q17: =IFERROR(P17/O17-1,"") | R17: 0 | S17: 0 | T17: =IFERROR(S17/R17-1,"") | U17: 0 | V17: 0 | W17: =IFERROR(V17/U17-1,"") | X17: 0 | Y17: 0 | Z17: =IFERROR(Y17/X17-1,"") | AA17: 0 | AB17: 0 | AC17: =IFERROR(AB17/AA17-1,"") | AD17: 0 | AE17: 0 | AF17: =IFERROR(AE17/AD17-1,"") | AG17: 0 | AH17: 0 | AI17: =IFERROR(AH17/AG17-1,"") | AJ17: 0 | AK17: 0 | AL17: =IFERROR(AK17/AJ17-1,"")
B18: Préstamos solicitados a socios o accionistas | C18: 0 | D18: 0 | E18: =IFERROR(D18/C18-1,"") | F18: 0 | G18: 0 | H18: =IFERROR(G18/F18-1,"") | I18: 0 | J18: 0 | K18: =IFERROR(J18/I18-1,"") | L18: 0 | M18: 0 | N18: =IFERROR(M18/L18-1,"") | O18: 0 | P18: 0 | Q18: =IFERROR(P18/O18-1,"") | R18: 0 | S18: 0 | T18: =IFERROR(S18/R18-1,"") | U18: 0 | V18: 0 | W18: =IFERROR(V18/U18-1,"") | X18: 0 | Y18: 0 | Z18: =IFERROR(Y18/X18-1,"") | AA18: 0 | AB18: 0 | AC18: =IFERROR(AB18/AA18-1,"") | AD18: 0 | AE18: 0 | AF18: =IFERROR(AE18/AD18-1,"") | AG18: 0 | AH18: 0 | AI18: =IFERROR(AH18/AG18-1,"") | AJ18: 0 | AK18: 0 | AL18: =IFERROR(AK18/AJ18-1,"")
B19: Recaudo de préstamos realizados a empleados | C19: 3500000 | D19: 3500000 | E19: =IFERROR(D19/C19-1,"") -> 0 | F19: 0 | G19: 0 | H19: =IFERROR(G19/F19-1,"") | I19: 0 | J19: 0 | K19: =IFERROR(J19/I19-1,"") | L19: 0 | M19: 0 | N19: =IFERROR(M19/L19-1,"") | O19: 0 | P19: 1250000 | Q19: =IFERROR(P19/O19-1,"") | R19: 0 | S19: 0 | T19: =IFERROR(S19/R19-1,"") | U19: 0 | V19: 1250000 | W19: =IFERROR(V19/U19-1,"") | X19: 0 | Y19: 0 | Z19: =IFERROR(Y19/X19-1,"") | AA19: 0 | AB19: 0 | AC19: =IFERROR(AB19/AA19-1,"") | AD19: 0 | AE19: 0 | AF19: =IFERROR(AE19/AD19-1,"") | AG19: 0 | AH19: 0 | AI19: =IFERROR(AH19/AG19-1,"") | AJ19: 0 | AK19: 0 | AL19: =IFERROR(AK19/AJ19-1,"")
B20: Ventas de propiedad, planta y equipo | C20: 0 | D20: 0 | E20: =IFERROR(D20/C20-1,"") | F20: 0 | G20: 0 | H20: =IFERROR(G20/F20-1,"") | I20: 0 | J20: 0 | K20: =IFERROR(J20/I20-1,"") | L20: 0 | M20: 0 | N20: =IFERROR(M20/L20-1,"") | O20: 0 | P20: 0 | Q20: =IFERROR(P20/O20-1,"") | R20: 0 | S20: 0 | T20: =IFERROR(S20/R20-1,"") | U20: 0 | V20: 0 | W20: =IFERROR(V20/U20-1,"") | X20: 0 | Y20: 0 | Z20: =IFERROR(Y20/X20-1,"") | AA20: 0 | AB20: 0 | AC20: =IFERROR(AB20/AA20-1,"") | AD20: 0 | AE20: 0 | AF20: =IFERROR(AE20/AD20-1,"") | AG20: 0 | AH20: 0 | AI20: =IFERROR(AH20/AG20-1,"") | AJ20: 0 | AK20: 0 | AL20: =IFERROR(AK20/AJ20-1,"")
B21: Venta de activos intangibles | C21: 0 | D21: 0 | E21: =IFERROR(D21/C21-1,"") | F21: 0 | G21: 0 | H21: =IFERROR(G21/F21-1,"") | I21: 0 | J21: 0 | K21: =IFERROR(J21/I21-1,"") | L21: 0 | M21: 0 | N21: =IFERROR(M21/L21-1,"") | O21: 0 | P21: 0 | Q21: =IFERROR(P21/O21-1,"") | R21: 0 | S21: 0 | T21: =IFERROR(S21/R21-1,"") | U21: 0 | V21: 0 | W21: =IFERROR(V21/U21-1,"") | X21: 0 | Y21: 0 | Z21: =IFERROR(Y21/X21-1,"") | AA21: 0 | AB21: 0 | AC21: =IFERROR(AB21/AA21-1,"") | AD21: 0 | AE21: 0 | AF21: =IFERROR(AE21/AD21-1,"") | AG21: 0 | AH21: 0 | AI21: =IFERROR(AH21/AG21-1,"") | AJ21: 0 | AK21: 0 | AL21: =IFERROR(AK21/AJ21-1,"")
B22: Intereses financieros recibidos | C22: 8500000 | D22: 8524000 | E22: =IFERROR(D22/C22-1,"") -> 0.0028235294 | F22: 8500000 | G22: 8615000 | H22: =IFERROR(G22/F22-1,"") -> 0.013529412 | I22: 8500000 | J22: 8599000 | K22: =IFERROR(J22/I22-1,"") -> 0.011647059 | L22: 8500000 | M22: 8733000 | N22: =IFERROR(M22/L22-1,"") -> 0.027411765 | O22: 8500000 | P22: 8666000 | Q22: =IFERROR(P22/O22-1,"") -> 0.019529412 | R22: 8500000 | S22: 7999000 | T22: =IFERROR(S22/R22-1,"") -> -0.058941176 | U22: 8500000 | V22: 8666000 | W22: =IFERROR(V22/U22-1,"") -> 0.019529412 | X22: 8500000 | Y22: 8326950 | Z22: =IFERROR(Y22/X22-1,"") -> -0.020358824 | AA22: 8500000 | AB22: 8000500 | AC22: =IFERROR(AB22/AA22-1,"") -> -0.058764706 | AD22: 8500000 | AE22: 8459610 | AF22: =IFERROR(AE22/AD22-1,"") -> -0.0047517647 | AG22: 8500000 | AH22: 8777050 | AI22: =IFERROR(AH22/AG22-1,"") -> 0.032594118 | AJ22: 8500000 | AK22: 8601000 | AL22: =IFERROR(AK22/AJ22-1,"") -> 0.011882353
B23: Dividendos y participaciones recibidos | C23: 0 | D23: 0 | E23: =IFERROR(D23/C23-1,"") | F23: 0 | G23: 0 | H23: =IFERROR(G23/F23-1,"") | I23: 0 | J23: 0 | K23: =IFERROR(J23/I23-1,"") | L23: 0 | M23: 0 | N23: =IFERROR(M23/L23-1,"") | O23: 0 | P23: 0 | Q23: =IFERROR(P23/O23-1,"") | R23: 0 | S23: 0 | T23: =IFERROR(S23/R23-1,"") | U23: 0 | V23: 0 | W23: =IFERROR(V23/U23-1,"") | X23: 0 | Y23: 0 | Z23: =IFERROR(Y23/X23-1,"") | AA23: 0 | AB23: 0 | AC23: =IFERROR(AB23/AA23-1,"") | AD23: 0 | AE23: 0 | AF23: =IFERROR(AE23/AD23-1,"") | AG23: 0 | AH23: 0 | AI23: =IFERROR(AH23/AG23-1,"") | AJ23: 0 | AK23: 0 | AL23: =IFERROR(AK23/AJ23-1,"")
B24: Devolución de impuestos | C24: 0 | D24: 0 | E24: =IFERROR(D24/C24-1,"") | F24: 20000000 | G24: 20000000 | H24: =IFERROR(G24/F24-1,"") -> 0 | I24: 0 | J24: 0 | K24: =IFERROR(J24/I24-1,"") | L24: 0 | M24: 0 | N24: =IFERROR(M24/L24-1,"") | O24: 0 | P24: 0 | Q24: =IFERROR(P24/O24-1,"") | R24: 0 | S24: 0 | T24: =IFERROR(S24/R24-1,"") | U24: 0 | V24: 0 | W24: =IFERROR(V24/U24-1,"") | X24: 0 | Y24: 0 | Z24: =IFERROR(Y24/X24-1,"") | AA24: 0 | AB24: 0 | AC24: =IFERROR(AB24/AA24-1,"") | AD24: 0 | AE24: 0 | AF24: =IFERROR(AE24/AD24-1,"") | AG24: 0 | AH24: 0 | AI24: =IFERROR(AH24/AG24-1,"") | AJ24: 0 | AK24: 0 | AL24: =IFERROR(AK24/AJ24-1,"")
B25: Otras entradas | C25: 0 | D25: 0 | E25: =IFERROR(D25/C25-1,"") | F25: 0 | G25: 0 | H25: =IFERROR(G25/F25-1,"") | I25: 0 | J25: 5000000 | K25: =IFERROR(J25/I25-1,"") | L25: 0 | M25: 0 | N25: =IFERROR(M25/L25-1,"") | O25: 0 | P25: 0 | Q25: =IFERROR(P25/O25-1,"") | R25: 0 | S25: 0 | T25: =IFERROR(S25/R25-1,"") | U25: 0 | V25: 0 | W25: =IFERROR(V25/U25-1,"") | X25: 0 | Y25: 0 | Z25: =IFERROR(Y25/X25-1,"") | AA25: 0 | AB25: 0 | AC25: =IFERROR(AB25/AA25-1,"") | AD25: 0 | AE25: 0 | AF25: =IFERROR(AE25/AD25-1,"") | AG25: 0 | AH25: 4500000 | AI25: =IFERROR(AH25/AG25-1,"") | AJ25: 0 | AK25: 0 | AL25: =IFERROR(AK25/AJ25-1,"")
B26: Total de entradas | C26: =SUM(C15:C25) -> 117000000 | D26: =SUM(D15:D25) -> 110713000 | E26: =IFERROR(D26/C26-1,"") -> -0.053735043 | F26: =SUM(F15:F25) -> 133500000 | G26: =SUM(G15:G25) -> 123865000 | H26: =IFERROR(G26/F26-1,"") -> -0.072172285 | I26: =SUM(I15:I25) -> 113500000 | J26: =SUM(J15:J25) -> 121139000 | K26: =IFERROR(J26/I26-1,"") -> 0.067303965 | L26: =SUM(L15:L25) -> 126500000 | M26: =SUM(M15:M25) -> 123733000 | N26: =IFERROR(M26/L26-1,"") -> -0.021873518 | O26: =SUM(O15:O25) -> 126500000 | P26: =SUM(P15:P25) -> 116036000 | Q26: =IFERROR(P26/O26-1,"") -> -0.082719368 | R26: =SUM(R15:R25) -> 126500000 | S26: =SUM(S15:S25) -> 124912000 | T26: =IFERROR(S26/R26-1,"") -> -0.01255336 | U26: =SUM(U15:U25) -> 138500000 | V26: =SUM(V15:V25) -> 117916000 | W26: =IFERROR(V26/U26-1,"") -> -0.14862094 | X26: =SUM(X15:X25) -> 138500000 | Y26: =SUM(Y15:Y25) -> 133082950 | Z26: =IFERROR(Y26/X26-1,"") -> -0.039112274 | AA26: =SUM(AA15:AA25) -> 138500000 | AB26: =SUM(AB15:AB25) -> 135914500 | AC26: =IFERROR(AB26/AA26-1,"") -> -0.01866787 | AD26: =SUM(AD15:AD25) -> 161500000 | AE26: =SUM(AE15:AE25) -> 142258610 | AF26: =IFERROR(AE26/AD26-1,"") -> -0.11914173 | AG26: =SUM(AG15:AG25) -> 161500000 | AH26: =SUM(AH15:AH25) -> 160782050 | AI26: =IFERROR(AH26/AG26-1,"") -> -0.0044455108 | AJ26: =SUM(AJ15:AJ25) -> 161500000 | AK26: =SUM(AK15:AK25) -> 166960000 | AL26: =IFERROR(AK26/AJ26-1,"") -> 0.03380805
B28: $$ Disponible | C28: =C12+C26 -> 228000000 | D28: =D12+D26 -> 223046000 | E28: =IFERROR(D28/C28-1,"") -> -0.02172807 | F28: =F12+F26 -> 265000000 | G28: =G12+G26 -> 249086000 | H28: =IFERROR(G28/F28-1,"") -> -0.06005283 | I28: =I12+I26 -> 293000000 | J28: =J12+J26 -> 278392000 | K28: =IFERROR(J28/I28-1,"") -> -0.049856655 | L28: =L12+L26 -> 312000000 | M28: =M12+M26 -> 289017000 | N28: =IFERROR(M28/L28-1,"") -> -0.073663462 | O28: =O12+O26 -> 346000000 | P28: =P12+P26 -> 314523000 | Q28: =IFERROR(P28/O28-1,"") -> -0.090973988 | R28: =R12+R26 -> 353000000 | S28: =S12+S26 -> 334435000 | T28: =IFERROR(S28/R28-1,"") -> -0.052592068 | U28: =U12+U26 -> 401000000 | V28: =V12+V26 -> 365324000 | W28: =IFERROR(V28/U28-1,"") -> -0.088967581 | X28: =X12+X26 -> 433000000 | Y28: =Y12+Y26 -> 389987950 | Z28: =IFERROR(Y28/X28-1,"") -> -0.099334988 | AA28: =AA12+AA26 -> 471000000 | AB28: =AB12+AB26 -> 425703450 | AC28: =IFERROR(AB28/AA28-1,"") -> -0.096171019 | AD28: =AD12+AD26 -> 528000000 | AE28: =AE12+AE26 -> 467177460 | AF28: =IFERROR(AE28/AD28-1,"") -> -0.1151942 | AG28: =AG12+AG26 -> 579000000 | AH28: =AH12+AH26 -> 524499510 | AI28: =IFERROR(AH28/AG28-1,"") -> -0.094128653 | AJ28: =AJ12+AJ26 -> 628000000 | AK28: =AK12+AK26 -> 583293510 | AL28: =IFERROR(AK28/AJ28-1,"") -> -0.071188678
B30: Salidas
B31: Pago a proveedores | C31: 30000000 | D31: 35000000 | E31: =IFERROR(D31/C31-1,"") -> 0.16666667 | F31: 30000000 | G31: 33000000 | H31: =IFERROR(G31/F31-1,"") -> 0.1 | I31: 30000000 | J31: 29000000 | K31: =IFERROR(J31/I31-1,"") -> -0.033333333 | L31: 33000000 | M31: 35000000 | N31: =IFERROR(M31/L31-1,"") -> 0.060606061 | O31: 33000000 | P31: 17000000 | Q31: =IFERROR(P31/O31-1,"") -> -0.48484848 | R31: 33000000 | S31: 31500000 | T31: =IFERROR(S31/R31-1,"") -> -0.045454545 | U31: 35000000 | V31: 37000000 | W31: =IFERROR(V31/U31-1,"") -> 0.057142857 | X31: 35000000 | Y31: 36528000 | Z31: =IFERROR(Y31/X31-1,"") -> 0.043657143 | AA31: 35000000 | AB31: 32222000 | AC31: =IFERROR(AB31/AA31-1,"") -> -0.079371429 | AD31: 38000000 | AE31: 35490000 | AF31: =IFERROR(AE31/AD31-1,"") -> -0.066052632 | AG31: 38000000 | AH31: 37123000 | AI31: =IFERROR(AH31/AG31-1,"") -> -0.023078947 | AJ31: 38000000 | AK31: 35000000 | AL31: =IFERROR(AK31/AJ31-1,"") -> -0.078947368
B32: Pago de servicios públicos | C32: 20000000 | D32: 18925000 | E32: =IFERROR(D32/C32-1,"") -> -0.05375 | F32: 20000000 | G32: 21500000 | H32: =IFERROR(G32/F32-1,"") -> 0.075 | I32: 20000000 | J32: 19666000 | K32: =IFERROR(J32/I32-1,"") -> -0.0167 | L32: 22000000 | M32: 20030000 | N32: =IFERROR(M32/L32-1,"") -> -0.089545455 | O32: 22000000 | P32: 20500000 | Q32: =IFERROR(P32/O32-1,"") -> -0.068181818 | R32: 22000000 | S32: 19777000 | T32: =IFERROR(S32/R32-1,"") -> -0.10104545 | U32: 25000000 | V32: 22500000 | W32: =IFERROR(V32/U32-1,"") -> -0.1 | X32: 25000000 | Y32: 22659000 | Z32: =IFERROR(Y32/X32-1,"") -> -0.09364 | AA32: 25000000 | AB32: 22049000 | AC32: =IFERROR(AB32/AA32-1,"") -> -0.11804 | AD32: 27000000 | AE32: 23615000 | AF32: =IFERROR(AE32/AD32-1,"") -> -0.12537037 | AG32: 27000000 | AH32: 24010000 | AI32: =IFERROR(AH32/AG32-1,"") -> -0.11074074 | AJ32: 27000000 | AK32: 25789000 | AL32: =IFERROR(AK32/AJ32-1,"") -> -0.044851852
B33: Pago de nómina | C33: 30000000 | D33: 26500000 | E33: =IFERROR(D33/C33-1,"") -> -0.11666667 | F33: 30000000 | G33: 30000000 | H33: =IFERROR(G33/F33-1,"") -> 0 | I33: 30000000 | J33: 28500000 | K33: =IFERROR(J33/I33-1,"") -> -0.05 | L33: 30000000 | M33: 28500000 | N33: =IFERROR(M33/L33-1,"") -> -0.05 | O33: 30000000 | P33: 28500000 | Q33: =IFERROR(P33/O33-1,"") -> -0.05 | R33: 30000000 | S33: 30000000 | T33: =IFERROR(S33/R33-1,"") -> 0 | U33: 30000000 | V33: 31500000 | W33: =IFERROR(V33/U33-1,"") -> 0.05 | X33: 30000000 | Y33: 31500000 | Z33: =IFERROR(Y33/X33-1,"") -> 0.05 | AA33: 30000000 | AB33: 31500000 | AC33: =IFERROR(AB33/AA33-1,"") -> 0.05 | AD33: 33000000 | AE33: 31500000 | AF33: =IFERROR(AE33/AD33-1,"") -> -0.045454545 | AG33: 33000000 | AH33: 31500000 | AI33: =IFERROR(AH33/AG33-1,"") -> -0.045454545 | AJ33: 33000000 | AK33: 35000000 | AL33: =IFERROR(AK33/AJ33-1,"") -> 0.060606061
B34: Pago por arrendamiento | C34: 0 | D34: 0 | E34: =IFERROR(D34/C34-1,"") | F34: 0 | G34: 0 | H34: =IFERROR(G34/F34-1,"") | I34: 0 | J34: 0 | K34: =IFERROR(J34/I34-1,"") | L34: 0 | M34: 0 | N34: =IFERROR(M34/L34-1,"") | O34: 0 | P34: 0 | Q34: =IFERROR(P34/O34-1,"") | R34: 0 | S34: 0 | T34: =IFERROR(S34/R34-1,"") | U34: 0 | V34: 0 | W34: =IFERROR(V34/U34-1,"") | X34: 0 | Y34: 0 | Z34: =IFERROR(Y34/X34-1,"") | AA34: 0 | AB34: 0 | AC34: =IFERROR(AB34/AA34-1,"") | AD34: 0 | AE34: 0 | AF34: =IFERROR(AE34/AD34-1,"") | AG34: 0 | AH34: 0 | AI34: =IFERROR(AH34/AG34-1,"") | AJ34: 0 | AK34: 0 | AL34: =IFERROR(AK34/AJ34-1,"")
B35: Pagos por publicidad | C35: 4000000 | D35: 5000000 | E35: =IFERROR(D35/C35-1,"") -> 0.25 | F35: 0 | G35: 0 | H35: =IFERROR(G35/F35-1,"") | I35: 4000000 | J35: 5000000 | K35: =IFERROR(J35/I35-1,"") -> 0.25 | L35: 0 | M35: 0 | N35: =IFERROR(M35/L35-1,"") | O35: 4000000 | P35: 5000000 | Q35: =IFERROR(P35/O35-1,"") -> 0.25 | R35: 0 | S35: 0 | T35: =IFERROR(S35/R35-1,"") | U35: 4000000 | V35: 5000000 | W35: =IFERROR(V35/U35-1,"") -> 0.25 | X35: 0 | Y35: 0 | Z35: =IFERROR(Y35/X35-1,"") | AA35: 4000000 | AB35: 5000000 | AC35: =IFERROR(AB35/AA35-1,"") -> 0.25 | AD35: 0 | AE35: 0 | AF35: =IFERROR(AE35/AD35-1,"") | AG35: 4000000 | AH35: 5000000 | AI35: =IFERROR(AH35/AG35-1,"") -> 0.25 | AJ35: 0 | AK35: 0 | AL35: =IFERROR(AK35/AJ35-1,"")
B36: Pagos por asesorías | C36: 3000000 | D36: 3000000 | E36: =IFERROR(D36/C36-1,"") -> 0 | F36: 3000000 | G36: 3000000 | H36: =IFERROR(G36/F36-1,"") -> 0 | I36: 3000000 | J36: 3000000 | K36: =IFERROR(J36/I36-1,"") -> 0 | L36: 3000000 | M36: 3000000 | N36: =IFERROR(M36/L36-1,"") -> 0 | O36: 3000000 | P36: 3000000 | Q36: =IFERROR(P36/O36-1,"") -> 0 | R36: 3000000 | S36: 3000000 | T36: =IFERROR(S36/R36-1,"") -> 0 | U36: 3000000 | V36: 3000000 | W36: =IFERROR(V36/U36-1,"") -> 0 | X36: 3000000 | Y36: 3000000 | Z36: =IFERROR(Y36/X36-1,"") -> 0 | AA36: 3000000 | AB36: 3000000 | AC36: =IFERROR(AB36/AA36-1,"") -> 0 | AD36: 3000000 | AE36: 3000000 | AF36: =IFERROR(AE36/AD36-1,"") -> 0 | AG36: 3000000 | AH36: 3000000 | AI36: =IFERROR(AH36/AG36-1,"") -> 0 | AJ36: 3000000 | AK36: 3000000 | AL36: =IFERROR(AK36/AJ36-1,"") -> 0
B37: Pagos por reparaciones y mantenimiento | C37: 2000000 | D37: 2000000 | E37: =IFERROR(D37/C37-1,"") -> 0 | F37: 0 | G37: 0 | H37: =IFERROR(G37/F37-1,"") | I37: 0 | J37: 0 | K37: =IFERROR(J37/I37-1,"") | L37: 2000000 | M37: 2000000 | N37: =IFERROR(M37/L37-1,"") -> 0 | O37: 0 | P37: 0 | Q37: =IFERROR(P37/O37-1,"") | R37: 0 | S37: 0 | T37: =IFERROR(S37/R37-1,"") | U37: 2000000 | V37: 2000000 | W37: =IFERROR(V37/U37-1,"") -> 0 | X37: 0 | Y37: 0 | Z37: =IFERROR(Y37/X37-1,"") | AA37: 0 | AB37: 0 | AC37: =IFERROR(AB37/AA37-1,"") | AD37: 2000000 | AE37: 2500000 | AF37: =IFERROR(AE37/AD37-1,"") -> 0.25 | AG37: 0 | AH37: 0 | AI37: =IFERROR(AH37/AG37-1,"") | AJ37: 0 | AK37: 0 | AL37: =IFERROR(AK37/AJ37-1,"")
B38: Pagos a otros acreedores | C38: 0 | D38: 0 | E38: =IFERROR(D38/C38-1,"") | F38: 0 | G38: 2000000 | H38: =IFERROR(G38/F38-1,"") | I38: 0 | J38: 0 | K38: =IFERROR(J38/I38-1,"") | L38: 0 | M38: 0 | N38: =IFERROR(M38/L38-1,"") | O38: 0 | P38: 0 | Q38: =IFERROR(P38/O38-1,"") | R38: 0 | S38: 0 | T38: =IFERROR(S38/R38-1,"") | U38: 0 | V38: 0 | W38: =IFERROR(V38/U38-1,"") | X38: 0 | Y38: 0 | Z38: =IFERROR(Y38/X38-1,"") | AA38: 0 | AB38: 0 | AC38: =IFERROR(AB38/AA38-1,"") | AD38: 0 | AE38: 0 | AF38: =IFERROR(AE38/AD38-1,"") | AG38: 0 | AH38: 0 | AI38: =IFERROR(AH38/AG38-1,"") | AJ38: 0 | AK38: 0 | AL38: =IFERROR(AK38/AJ38-1,"")
B39: Pagos por seguros | C39: 0 | D39: 0 | E39: =IFERROR(D39/C39-1,"") | F39: 0 | G39: 0 | H39: =IFERROR(G39/F39-1,"") | I39: 13000000 | J39: 15000000 | K39: =IFERROR(J39/I39-1,"") -> 0.15384615 | L39: 0 | M39: 0 | N39: =IFERROR(M39/L39-1,"") | O39: 0 | P39: 0 | Q39: =IFERROR(P39/O39-1,"") | R39: 0 | S39: 0 | T39: =IFERROR(S39/R39-1,"") | U39: 0 | V39: 0 | W39: =IFERROR(V39/U39-1,"") | X39: 0 | Y39: 0 | Z39: =IFERROR(Y39/X39-1,"") | AA39: 0 | AB39: 0 | AC39: =IFERROR(AB39/AA39-1,"") | AD39: 0 | AE39: 0 | AF39: =IFERROR(AE39/AD39-1,"") | AG39: 0 | AH39: 0 | AI39: =IFERROR(AH39/AG39-1,"") | AJ39: 0 | AK39: 0 | AL39: =IFERROR(AK39/AJ39-1,"")
B40: Pago de impuesto de renta | C40: 0 | D40: 0 | E40: =IFERROR(D40/C40-1,"") | F40: 0 | G40: 0 | H40: =IFERROR(G40/F40-1,"") | I40: 0 | J40: 0 | K40: =IFERROR(J40/I40-1,"") | L40: 0 | M40: 0 | N40: =IFERROR(M40/L40-1,"") | O40: 20000000 | P40: 25000000 | Q40: =IFERROR(P40/O40-1,"") -> 0.25 | R40: 0 | S40: 0 | T40: =IFERROR(S40/R40-1,"") | U40: 0 | V40: 0 | W40: =IFERROR(V40/U40-1,"") | X40: 0 | Y40: 0 | Z40: =IFERROR(Y40/X40-1,"") | AA40: 0 | AB40: 0 | AC40: =IFERROR(AB40/AA40-1,"") | AD40: 0 | AE40: 0 | AF40: =IFERROR(AE40/AD40-1,"") | AG40: 0 | AH40: 0 | AI40: =IFERROR(AH40/AG40-1,"") | AJ40: 0 | AK40: 0 | AL40: =IFERROR(AK40/AJ40-1,"")
B41: Pago de IVA | C41: 5000000 | D41: 4000000 | E41: =IFERROR(D41/C41-1,"") -> -0.2 | F41: 0 | G41: 0 | H41: =IFERROR(G41/F41-1,"") | I41: 5000000 | J41: 3300000 | K41: =IFERROR(J41/I41-1,"") -> -0.34 | L41: 0 | M41: 0 | N41: =IFERROR(M41/L41-1,"") | O41: 5000000 | P41: 3500000 | Q41: =IFERROR(P41/O41-1,"") -> -0.3 | R41: 0 | S41: 0 | T41: =IFERROR(S41/R41-1,"") | U41: 5000000 | V41: 3230000 | W41: =IFERROR(V41/U41-1,"") -> -0.354 | X41: 5000000 | Y41: 3724000 | Z41: =IFERROR(Y41/X41-1,"") -> -0.2552 | AA41: 5000000 | AB41: 4014000 | AC41: =IFERROR(AB41/AA41-1,"") -> -0.1972 | AD41: 5000000 | AE41: 4226000 | AF41: =IFERROR(AE41/AD41-1,"") -> -0.1548 | AG41: 5000000 | AH41: 4500000 | AI41: =IFERROR(AH41/AG41-1,"") -> -0.1 | AJ41: 5000000 | AK41: 4956000 | AL41: =IFERROR(AK41/AJ41-1,"") -> -0.0088
B42: Pago de impuesto al consumo | C42: 0 | D42: 0 | E42: =IFERROR(D42/C42-1,"") | F42: 0 | G42: 0 | H42: =IFERROR(G42/F42-1,"") | I42: 0 | J42: 0 | K42: =IFERROR(J42/I42-1,"") | L42: 0 | M42: 0 | N42: =IFERROR(M42/L42-1,"") | O42: 0 | P42: 0 | Q42: =IFERROR(P42/O42-1,"") | R42: 0 | S42: 0 | T42: =IFERROR(S42/R42-1,"") | U42: 0 | V42: 0 | W42: =IFERROR(V42/U42-1,"") | X42: 0 | Y42: 0 | Z42: =IFERROR(Y42/X42-1,"") | AA42: 0 | AB42: 0 | AC42: =IFERROR(AB42/AA42-1,"") | AD42: 0 | AE42: 0 | AF42: =IFERROR(AE42/AD42-1,"") | AG42: 0 | AH42: 0 | AI42: =IFERROR(AH42/AG42-1,"") | AJ42: 0 | AK42: 0 | AL42: =IFERROR(AK42/AJ42-1,"")
... B51: Otros pagos | C51: 0 | D51: 0 | E51: =IFERROR(D51/C51-1,"") | F51: 0 | G51: 0 | H51: =IFERROR(G51/F51-1,"") | I51: 0 | J51: 7000000 | K51: =IFERROR(J51/I51-1,"") | L51: 0 | M51: 0 | N51: =IFERROR(M51/L51-1,"") | O51: 0 | P51: 0 | Q51: =IFERROR(P51/O51-1,"") | R51: 0 | S51: 0 | T51: =IFERROR(S51/R51-1,"") | U51: 0 | V51: 1689000 | W51: =IFERROR(V51/U51-1,"") | X51: 0 | Y51: 0 | Z51: =IFERROR(Y51/X51-1,"") | AA51: 0 | AB51: 0 | AC51: =IFERROR(AB51/AA51-1,"") | AD51: 0 | AE51: 0 | AF51: =IFERROR(AE51/AD51-1,"") | AG51: 0 | AH51: 0 | AI51: =IFERROR(AH51/AG51-1,"") | AJ51: 0 | AK51: 5567000 | AL51: =IFERROR(AK51/AJ51-1,"")
B53: Total de salidas | C53: =SUM(C31:C51) -> 96500000 | D53: =SUM(D31:D51) -> 97825000 | E53: =IFERROR(D53/C53-1,"") -> 0.01373057 | F53: =SUM(F31:F51) -> 85500000 | G53: =SUM(G31:G51) -> 91833000 | H53: =IFERROR(G53/F53-1,"") -> 0.074070175 | I53: =SUM(I31:I51) -> 107500000 | J53: =SUM(J31:J51) -> 113108000 | K53: =IFERROR(J53/I53-1,"") -> 0.052167442 | L53: =SUM(L31:L51) -> 92500000 | M53: =SUM(M31:M51) -> 90530000 | N53: =IFERROR(M53/L53-1,"") -> -0.021297297 | O53: =SUM(O31:O51) -> 119500000 | P53: =SUM(P31:P51) -> 105000000 | Q53: =IFERROR(P53/O53-1,"") -> -0.12133891 | R53: =SUM(R31:R51) -> 90500000 | S53: =SUM(S31:S51) -> 87027000 | T53: =IFERROR(S53/R53-1,"") -> -0.038375691 | U53: =SUM(U31:U51) -> 106500000 | V53: =SUM(V31:V51) -> 108419000 | W53: =IFERROR(V53/U53-1,"") -> 0.018018779 | X53: =SUM(X31:X51) -> 100500000 | Y53: =SUM(Y31:Y51) -> 100199000 | Z53: =IFERROR(Y53/X53-1,"") -> -0.0029950249 | AA53: =SUM(AA31:AA51) -> 104500000 | AB53: =SUM(AB31:AB51) -> 100784600 | AC53: =IFERROR(AB53/AA53-1,"") -> -0.035554067 | AD53: =SUM(AD31:AD51) -> 110500000 | AE53: =SUM(AE31:AE51) -> 103460000 | AF53: =IFERROR(AE53/AD53-1,"") -> -0.063710407 | AG53: =SUM(AG31:AG51) -> 112500000 | AH53: =SUM(AH31:AH51) -> 108166000 | AI53: =IFERROR(AH53/AG53-1,"") -> -0.038524444 | AJ53: =SUM(AJ31:AJ51) -> 108500000 | AK53: =SUM(AK31:AK51) -> 114994000 | AL53: =IFERROR(AK53/AJ53-1,"") -> 0.059852535
B55: Sobrante (o faltante) del mes | C55: =C26-C53 -> 20500000 | D55: =D26-D53 -> 12888000 | E55: =IFERROR(D55/C55-1,"") -> -0.37131707 | F55: =F26-F53 -> 48000000 | G55: =G26-G53 -> 32032000 | H55: =IFERROR(G55/F55-1,"") -> -0.33266667 | I55: =I26-I53 -> 6000000 | J55: =J26-J53 -> 8031000 | K55: =IFERROR(J55/I55-1,"") -> 0.3385 | L55: =L26-L53 -> 34000000 | M55: =M26-M53 -> 33203000 | N55: =IFERROR(M55/L55-1,"") -> -0.023441176 | O55: =O26-O53 -> 7000000 | P55: =P26-P53 -> 11036000 | Q55: =IFERROR(P55/O55-1,"") -> 0.57657143 | R55: =R26-R53 -> 36000000 | S55: =S26-S53 -> 37885000 | T55: =IFERROR(S55/R55-1,"") -> 0.052361111 | U55: =U26-U53 -> 32000000 | V55: =V26-V53 -> 9497000 | W55: =IFERROR(V55/U55-1,"") -> -0.70321875 | X55: =X26-X53 -> 38000000 | Y55: =Y26-Y53 -> 32883950 | Z55: =IFERROR(Y55/X55-1,"") -> -0.13463289 | AA55: =AA26-AA53 -> 34000000 | AB55: =AB26-AB53 -> 35129900 | AC55: =IFERROR(AB55/AA55-1,"") -> 0.033232353 | AD55: =AD26-AD53 -> 51000000 | AE55: =AE26-AE53 -> 38798610 | AF55: =IFERROR(AE55/AD55-1,"") -> -0.23924294 | AG55: =AG26-AG53 -> 49000000 | AH55: =AH26-AH53 -> 52616050 | AI55: =IFERROR(AH55/AG55-1,"") -> 0.073796939 | AJ55: =AJ26-AJ53 -> 53000000 | AK55: =AK26-AK53 -> 51966000 | AL55: =IFERROR(AK55/AJ55-1,"") -> -0.019509434
B57: $$ Disponible al final del período | C57: =+C12+C55 -> 131500000 | D57: =+D12+D55 -> 125221000 | E57: =IFERROR(D57/C57-1,"") -> -0.047749049 | F57: =+F12+F55 -> 179500000 | G57: =+G12+G55 -> 157253000 | H57: =IFERROR(G57/F57-1,"") -> -0.12393872 | I57: =+I12+I55 -> 185500000 | J57: =+J12+J55 -> 165284000 | K57: =IFERROR(J57/I57-1,"") -> -0.10898113 | L57: =+L12+L55 -> 219500000 | M57: =+M12+M55 -> 198487000 | N57: =IFERROR(M57/L57-1,"") -> -0.095731207 | O57: =+O12+O55 -> 226500000 | P57: =+P12+P55 -> 209523000 | Q57: =IFERROR(P57/O57-1,"") -> -0.074953642 | R57: =+R12+R55 -> 262500000 | S57: =+S12+S55 -> 247408000 | T57: =IFERROR(S57/R57-1,"") -> -0.057493333 | U57: =+U12+U55 -> 294500000 | V57: =+V12+V55 -> 256905000 | W57: =IFERROR(V57/U57-1,"") -> -0.12765705 | X57: =+X12+X55 -> 332500000 | Y57: =+Y12+Y55 -> 289788950 | Z57: =IFERROR(Y57/X57-1,"") -> -0.12845429 | AA57: =+AA12+AA55 -> 366500000 | AB57: =+AB12+AB55 -> 324918850 | AC57: =IFERROR(AB57/AA57-1,"") -> -0.11345471 | AD57: =+AD12+AD55 -> 417500000 | AE57: =+AE12+AE55 -> 363717460 | AF57: =IFERROR(AE57/AD57-1,"") -> -0.12882046 | AG57: =+AG12+AG55 -> 466500000 | AH57: =+AH12+AH55 -> 416333510 | AI57: =IFERROR(AH57/AG57-1,"") -> -0.10753803 | AJ57: =+AJ12+AJ55 -> 519500000 | AK57: =+AK12+AK55 -> 468299510 | AL57: =IFERROR(AK57/AJ57-1,"") -> -0.098557247

Sheet Gráfico
B5: Comportamiento del disponible
B7: =+Introducción!B4 -> (Fecha de actualización: agosto 29 de 2024)
B9: Meses del año | C9: =+'Flujo de caja'!B57 -> $$ Disponible al final del período | E9: % Cumplimiento
C10: =+'Flujo de caja'!C11 -> Ppto | D10: =+'Flujo de caja'!D11 -> Real | E10: % cumplimiento
B11: =+'Flujo de caja'!C10 -> Enero | C11: =+'Flujo de caja'!C57/1000 -> 131500 | D11: =+'Flujo de caja'!D57/1000 -> 125221 | E11: =+D11/C11 -> 0.95225095
B12: =+'Flujo de caja'!F10 -> Febrero | C12: =+'Flujo de caja'!F57/1000 -> 179500 | D12: =+'Flujo de caja'!G57/1000 -> 157253 | E12: =+D12/C12 -> 0.87606128
B13: =+'Flujo de caja'!I10 -> Marzo | C13: =+'Flujo de caja'!I57/1000 -> 185500 | D13: =+'Flujo de caja'!J57/1000 -> 165284 | E13: =+D13/C13 -> 0.89101887
B14: =+'Flujo de caja'!L10 -> Abril | C14: =+'Flujo de caja'!L57/1000 -> 219500 | D14: =+'Flujo de caja'!M57/1000 -> 198487 | E14: =+D14/C14 -> 0.90426879
B15: =+'Flujo de caja'!O10 -> Mayo | C15: =+'Flujo de caja'!O57/1000 -> 226500 | D15: =+'Flujo de caja'!P57/1000 -> 209523 | E15: =+D15/C15 -> 0.92504636
B16: =+'Flujo de caja'!R10 -> Junio | C16: =+'Flujo de caja'!R57/1000 -> 262500 | D16: =+'Flujo de caja'!S57/1000 -> 247408 | E16: =+D16/C16 -> 0.94250667
B17: =+'Flujo de caja'!U10 -> Julio | C17: =+'Flujo de caja'!U57/1000 -> 294500 | D17: =+'Flujo de caja'!V57/1000 -> 256905 | E17: =+D17/C17 -> 0.87234295
B18: =+'Flujo de caja'!X10 -> Agosto | C18: =+'Flujo de caja'!X57/1000 -> 332500 | D18: =+'Flujo de caja'!Y57/1000 -> 289788.95 | E18: =+D18/C18 -> 0.87154571
B19: =+'Flujo de caja'!AA10 -> Septiembre | C19: =+'Flujo de caja'!AA57/1000 -> 366500 | D19: =+'Flujo de caja'!AB57/1000 -> 324918.85 | E19: =+D19/C19 -> 0.88654529
B20: =+'Flujo de caja'!AD10 -> Octubre | C20: =+'Flujo de caja'!AD57/1000 -> 417500 | D20: =+'Flujo de caja'!AE57/1000 -> 363717.46 | E20: =+D20/C20 -> 0.87117954
B21: =+'Flujo de caja'!AG10 -> Noviembre | C21: =+'Flujo de caja'!AG57/1000 -> 466500 | D21: =+'Flujo de caja'!AH57/1000 -> 416333.51 | E21: =+D21/C21 -> 0.89246197
B22: =+'Flujo de caja'!AJ10 -> Diciembre | C22: =+'Flujo de caja'!AJ57/1000 -> 519500 | D22: =+'Flujo de caja'!AK57/1000 -> 468299.51 | E22: =+D22/C22 -> 0.90144275

Sheet Listado completo de archivos 
A7: ESTE ES EL LISTADO COMPLETO DE LAS HERRAMIENTAS PUBLICADAS
A8: Fecha de actualización: agosto 29 de 2024
A9: Haz clic aquí para ver una versión actualizada de este listado
A10: IDEA: | B10: Si quieres buscar una herramienta en especial en este listado, dale "Buscar" en Excel (Ctrl + B, en casi todos lados).
B12: Ejercicio para la distribución de las rentas exentas y deducciones imputables limitadas en las personas naturales residentes (Resolución 000120 de 2024)
B14: Carta de finalización del contrato de arrendamiento por vencimiento del término
B16: Certificación de baja de inventarios por obsolescencia (Excel con macros)
B18: Modelo de notificación de sanción disciplinaria al trabajador
B20: Simulador para comparar créditos bancarios con tabla de amortización
B22: Modelo de pagaré en blanco y carta de instrucción
B24: Comparativo de normas de la Resolución 000165 de 2023 sobre facturación electrónica modificadas con la Resolución 000119 de 2024
B26: Formato de arqueo de caja general con macros
B28: Modelo en Word de acuerdo de pago
B30: Cálculo del límite de subcapitalización: casos prácticos en Excel
B32: Modelo de citación a descargos
B34: Modelo de carta de respuesta a la solicitud de un servicio
... B4674: [Liquidador] Modelo para elaborar un Resumen de Ajustes propuestos a los Estados Financieros en el desarrollo de una auditoría externa o Revisoría Fiscal
